trex_python/GMM_utils.py
trex_python/__init__.py
trex_python/networkAlgo.py
trex_python/regularization_gmm.py
trex_python/utility.py
trex_python-0.1.2.dist-info/LICENSE
trex_python-0.1.2.dist-info/METADATA
trex_python-0.1.2.dist-info/WHEEL
trex_python-0.1.2.dist-info/top_level.txt
trex_python-0.1.2.dist-info/RECORD
